zxtouch/__init__.py
zxtouch/client.py
zxtouch/colorsearchtasktypes.py
zxtouch/constants.py
zxtouch/datahandler.py
zxtouch/deviceinfotasktypes.py
zxtouch/kbdtasktypes.py
zxtouch/tasktypes.py
zxtouch/toasttypes.py
zxtouch/touchtypes.py
zxtouch-0.0.7.post11.dist-info/LICENSE
zxtouch-0.0.7.post11.dist-info/METADATA
zxtouch-0.0.7.post11.dist-info/WHEEL
zxtouch-0.0.7.post11.dist-info/top_level.txt
zxtouch-0.0.7.post11.dist-info/RECORD
