Metadata-Version: 2.1
Name: zxtouch
Version: 0.0.7.post11
Summary: iOS Automation Framework iOS Touch Simulation Library
Home-page: https://gitlab.com/marzzzello/zxtouch
Author: xuan32546, marzzzello
Author-email: zxtouch@07f.de
License: GPL-3.0
Platform: UNKNOWN
Requires-Python: >=3.7
License-File: LICENSE
